LICENSE
README.md
README.rst
setup.py
numlib/__init__.py
numlib/curves.py
numlib/elliptic_curves.py
numlib/finite_fields.py
numlib/modular_integers.py
numlib/py.typed
numlib/quotient_rings.py
numlib/test_zmodp.py
numlib/test_zmodp2.py
numlib/test_zmodp3.py
numlib/test_zmodp4.py
numlib/test_zmodp5.py
numlib/test_zmodp6.py
numlib/test_zmodp7.py
numlib/test_zmodp8.py
numlib/test_zmodp9.py
numlib/utils.py
numlib.egg-info/PKG-INFO
numlib.egg-info/SOURCES.txt
numlib.egg-info/dependency_links.txt
numlib.egg-info/not-zip-safe
numlib.egg-info/requires.txt
numlib.egg-info/top_level.txt
svgs/0087a0af2278153d57777b3ea0db2955.svg
svgs/0160bef1ca5087d29cf21b4cb7388b47.svg
svgs/01cd673fdadd974ed49cb0028a4ddf6d.svg
svgs/02362adb5475ae0b16399764036d399d.svg
svgs/03fdf3c6a83ab1f3f304bbc20f6cdadf.svg
svgs/0647ddb3ea161afc003c0d97d0727fa7.svg
svgs/0786a7b732d7242200d22552fe3630f1.svg
svgs/08388257ef92912ad5587b3d746bffa6.svg
svgs/09f485feb71728c385ea8299c839e059.svg
svgs/0a9a6cf9aecafe4d6b38b15898ed04e7.svg
svgs/0a9ab76eab686725329f060184eba64f.svg
svgs/0bc63b8ce7a9477572cb9c4efaf15a2b.svg
svgs/0c2c1f65379c26b522df68ef4108df07.svg
svgs/0f452ec0bcf578fa387e4857f80f03f4.svg
svgs/12203df97e68d3a4eb76cad4e219b469.svg
svgs/122d7384984d648b31748539d7b3d481.svg
svgs/1324004bc7c64764a79b0c6b8e2b6232.svg
svgs/136d89c226dc9cf5634cf7e18b2bdcfb.svg
svgs/14ace1d397989451df90d9bf22f2747a.svg
svgs/183c0fcbf5555289982cc209850085a7.svg
svgs/190083ef7a1625fbc75f243cffb9c96d.svg
svgs/19a6547de4d630abd6989ce1c99bb0ce.svg
svgs/1a28c5d56480e9954e44b8d36c15d351.svg
svgs/1bed9084d04362b70a2883bae1ff1bf0.svg
svgs/1c0ffa3cb8076e9cf412b81e771f20e0.svg
svgs/1c3dd52d9024d3d304422dd47538b15e.svg
svgs/1cbbdfe2c0c14d03cc2dd3865710a522.svg
svgs/1d16de38c895acda1e9ea06e45745969.svg
svgs/1d5408c61fb08ee34b974f8bce012835.svg
svgs/1da70e9963a3842a0405814a5a218802.svg
svgs/1e7097ee7ea18cca8abf23e2d617a6f3.svg
svgs/1fa2f3fab16e52d2d5bd3f757766daa9.svg
svgs/2012540586a66e3dc43394a218c44338.svg
svgs/2103f85b8b1477f430fc407cad462224.svg
svgs/2261788873d14dd272cdb92343f9c839.svg
svgs/2373b2f6e7b0d17338529bb5ba49121a.svg
svgs/2493a9c43a98e81daf070b0719f65430.svg
